odoo10_addon_account_invoice_factur_x-10.0.1.0.0.99.dev51-nspkg.pth
odoo/addons/account_invoice_factur-x/README.rst
odoo/addons/account_invoice_factur-x/__init__.py
odoo/addons/account_invoice_factur-x/__manifest__.py
odoo/addons/account_invoice_factur-x/post_install.py
odoo/addons/account_invoice_factur-x/i18n/account_invoice_factur-x.pot
odoo/addons/account_invoice_factur-x/i18n/de.po
odoo/addons/account_invoice_factur-x/i18n/es.po
odoo/addons/account_invoice_factur-x/i18n/fr.po
odoo/addons/account_invoice_factur-x/models/__init__.py
odoo/addons/account_invoice_factur-x/models/account_config_settings.py
odoo/addons/account_invoice_factur-x/models/account_invoice.py
odoo/addons/account_invoice_factur-x/models/company.py
odoo/addons/account_invoice_factur-x/models/report.py
odoo/addons/account_invoice_factur-x/static/description/icon.png
odoo/addons/account_invoice_factur-x/static/logos/factur-x-basic.png
odoo/addons/account_invoice_factur-x/static/logos/factur-x-basicwl.png
odoo/addons/account_invoice_factur-x/static/logos/factur-x-en16931.png
odoo/addons/account_invoice_factur-x/static/logos/factur-x-extended.png
odoo/addons/account_invoice_factur-x/static/logos/factur-x-minimum.png
odoo/addons/account_invoice_factur-x/tests/__init__.py
odoo/addons/account_invoice_factur-x/tests/test_facturx_invoice.py
odoo/addons/account_invoice_factur-x/views/account_config_settings.xml
odoo/addons/account_invoice_factur-x/views/report_invoice.xml
odoo/addons/account_invoice_factur-x/views/res_partner.xml
odoo10_addon_account_invoice_factur_x-10.0.1.0.0.99.dev51.dist-info/METADATA
odoo10_addon_account_invoice_factur_x-10.0.1.0.0.99.dev51.dist-info/WHEEL
odoo10_addon_account_invoice_factur_x-10.0.1.0.0.99.dev51.dist-info/namespace_packages.txt
odoo10_addon_account_invoice_factur_x-10.0.1.0.0.99.dev51.dist-info/top_level.txt
odoo10_addon_account_invoice_factur_x-10.0.1.0.0.99.dev51.dist-info/RECORD
